README.md
setup.py
src/librl/__init__.py
src/librl/calc.py
src/librl/hypers.py
src/librl/reward.py
src/librl/utils.py
src/librl.egg-info/PKG-INFO
src/librl.egg-info/SOURCES.txt
src/librl.egg-info/dependency_links.txt
src/librl.egg-info/top_level.txt
src/librl/agent/__init__.py
src/librl/agent/mdp.py
src/librl/agent/pg.py
src/librl/nn/__init__.py
src/librl/nn/actor.py
src/librl/nn/classifier.py
src/librl/nn/critic.py
src/librl/nn/pg_loss.py
src/librl/nn/policy.py
src/librl/nn/core/__init__.py
src/librl/nn/core/bilinear.py
src/librl/nn/core/cnn.py
src/librl/nn/core/mlp.py
src/librl/nn/core/rnn.py
src/librl/nn/core/sequential.py
src/librl/replay/__init__.py
src/librl/replay/episodic.py
src/librl/task/__init__.py
src/librl/task/base.py
src/librl/task/cc.py
src/librl/task/classification.py
src/librl/task/distribution.py
src/librl/task/problem.py
src/librl/train/__init__.py
src/librl/train/log.py
src/librl/train/train_loop.py
src/librl/train/cc/__init__.py
src/librl/train/cc/maml.py
src/librl/train/cc/pg.py
src/librl/train/classification/__init__.py
src/librl/train/classification/label.py