Metadata-Version: 1.2
Name: librl
Version: 0.2.5
Summary: Library for various DRL and DL projects.
Home-page: https://github.com/Matthew-McRaven/librl
Author: Matthew McRaven
Author-email: mkm302@georgetown.edu
License: UNKNOWN
Platform: UNKNOWN
Requires-Python: ~= 3.8
